Workbook

Sheet Ganhos
A1: SIMULADOR DE RECEITA - VENDA NAS MAQUINETAS
A3: TOTAL VENDAS | C3: 10000 | F3: 500000
B5: Receita Bruta | C5: Vendedor | D5: Meta Bônus | E5: Supervisor | F5: Ger. Comercial | G5: Regional | H5: Diretor | I5: Gestor | J5: Imposto 12% | K5: Lucro Líq.
A6: Tab A | B6: 250 | C6: =C3*1.5% -> 150 | D6: =C3*1% -> 100 | E6: =C3*0.25% -> 25 | F6: =C3*0.2% -> 20 | G6: =C3*0.1% -> 10 | H6: =C3*0.05% -> 5 | I6: =C3*0.2% -> 20 | J6: =B6*12% -> 30 | K6: =B6-D6-C6-E6-F6-G6-H6-I6-J6 -> -110
A7: Tab B | B7: ='20'!H5 -> 200 | C7: =C3*1.25% -> 125 | D7: =C3*1% -> 100 | E7: =C3*0.2% -> 20 | F7: =C3*0.15% -> 15 | G7: =C3*0.08% -> 8 | H7: =C3*0.03% -> 3 | I7: =C3*0.15% -> 15 | J7: =B7*12% -> 24 | K7: =B7-D7-C7-E7-F7-G7-H7-I7-J7 -> -110
A8: Tab C | B8: ='15'!H5 -> 150 | C8: =C3*1% -> 100 | D8: 0 | E8: =C3*0.15% -> 15 | F8: =C3*0.1% -> 10 | G8: =C3*0.05% -> 5 | H8: =C3*0.02% -> 2 | I8: =C3*0.1% -> 10 | J8: =B8*12% -> 18 | K8: =B8-D8-C8-E8-F8-G8-H8-I8-J8 -> -10
A9: Tab D | B9: ='10'!H5 -> 100 | C9: =C3*0.5% -> 50 | D9: 0 | E9: =C3*0.1% -> 10 | F9: =C3*0.05% -> 5 | G9: =C3*0.02% -> 2 | H9: =C3*0.01% -> 1 | I9: =C3*0.05% -> 5 | J9: =B9*12% -> 12 | K9: =B9-D9-C9-E9-F9-G9-H9-I9-J9 -> 15
A11: 13 | C11: 0.0949 | F11: 0.0882
A12: 14 | C12: 0.0897 | F12: 0.0836
A13: 15 | C13: 0.0841 | F13: 0.0796
A14: 16 | C14: 0.0791 | F14: 0.0749
A15: 17 | C15: 0.0747 | F15: 0.0708
A16: 18 | C16: 0.0708 | F16: 0.0672

Sheet Tabela
A1: SIMULADOR PADRÃO
A3: VALOR A RECEBER | C3: 1000
A5: PARCELAS | B5: TABELA A | D5: TABELA B | F5: TABELA C | H5: TABELA D
B6: Parcela | C6: Total | D6: Parcela | E6: Total | F6: Parcela | G6: Total | H6: Parcela | I6: Total
A7: 1X | B7: =C7 -> 1290.256 | C7: =$C$3*'25'!J9 -> 1290.256 | D7: =E7 -> 1238.6457 | E7: =$C$3*'20'!J9 -> 1238.6457 | F7: =G7 -> 1187.0355 | G7: =$C$3*'15'!J9 -> 1187.0355 | H7: =I7 -> 1135.4253 | I7: =$C$3*'10'!J9 -> 1135.4253
A8: 2X | B8: =C8/2 -> 652.53706 | C8: =$C$3*'25'!J11 -> 1305.0741 | D8: =E8/2 -> 626.43558 | E8: =$C$3*'20'!J11 -> 1252.8712 | F8: =G8/2 -> 600.3341 | G8: =$C$3*'15'!J11 -> 1200.6682 | H8: =I8/2 -> 574.23262 | I8: =$C$3*'10'!J11 -> 1148.4652
A9: 3X | B9: =C9/3 -> 437.81304 | C9: =$C$3*'25'!J12 -> 1313.4391 | D9: =E9/3 -> 420.30051 | E9: =$C$3*'20'!J12 -> 1260.9015 | F9: =G9/3 -> 402.78799 | G9: =$C$3*'15'!J12 -> 1208.364 | H9: =I9/3 -> 385.27547 | I9: =$C$3*'10'!J12 -> 1155.8264
A10: 4X | B10: =C10/4 -> 330.478 | C10: =$C$3*'25'!J13 -> 1321.912 | D10: =E10/4 -> 317.25888 | E10: =$C$3*'20'!J13 -> 1269.0355 | F10: =G10/4 -> 304.03976 | G10: =$C$3*'15'!J13 -> 1216.1591 | H10: =I10/4 -> 290.82064 | I10: =$C$3*'10'!J13 -> 1163.2826
A11: 5X | B11: =C11/5 -> 266.09899 | C11: =$C$3*'25'!J14 -> 1330.4949 | D11: =E11/5 -> 255.45503 | E11: =$C$3*'20'!J14 -> 1277.2751 | F11: =G11/5 -> 244.81107 | G11: =$C$3*'15'!J14 -> 1224.0553 | H11: =I11/5 -> 234.16711 | I11: =$C$3*'10'!J14 -> 1170.8356
A12: 6X | B12: =C12/6 -> 223.15053 | C12: =$C$3*'25'!J15 -> 1338.9032 | D12: =E12/6 -> 214.22451 | E12: =$C$3*'20'!J15 -> 1285.347 | F12: =G12/6 -> 205.29849 | G12: =$C$3*'15'!J15 -> 1231.7909 | H12: =I12/6 -> 196.37247 | I12: =$C$3*'10'!J15 -> 1178.2348
A13: 7X | B13: =C13/7 -> 192.50909 | C13: =$C$3*'25'!J16 -> 1347.5636 | D13: =E13/7 -> 184.80872 | E13: =$C$3*'20'!J16 -> 1293.6611 | F13: =G13/7 -> 177.10836 | G13: =$C$3*'15'!J16 -> 1239.7585 | H13: =I13/7 -> 169.408 | I13: =$C$3*'10'!J16 -> 1185.856
A14: 8X | B14: =C14/8 -> 169.50532 | C14: =$C$3*'25'!J17 -> 1356.0425 | D14: =E14/8 -> 162.7251 | E14: =$C$3*'20'!J17 -> 1301.8008 | F14: =G14/8 -> 155.94489 | G14: =$C$3*'15'!J17 -> 1247.5591 | H14: =I14/8 -> 149.16468 | I14: =$C$3*'10'!J17 -> 1193.3174
A15: 9X | B15: =C15/9 -> 151.64198 | C15: =$C$3*'25'!J18 -> 1364.7778 | D15: =E15/9 -> 145.5763 | E15: =$C$3*'20'!J18 -> 1310.1867 | F15: =G15/9 -> 139.51062 | G15: =$C$3*'15'!J18 -> 1255.5956 | H15: =I15/9 -> 133.44494 | I15: =$C$3*'10'!J18 -> 1201.0045
A16: 10X | B16: =C16/10 -> 137.6652 | C16: =$C$3*'25'!J19 -> 1376.652 | D16: =E16/10 -> 132.15859 | E16: =$C$3*'20'!J19 -> 1321.5859 | F16: =G16/10 -> 126.65198 | G16: =$C$3*'15'!J19 -> 1266.5198 | H16: =I16/10 -> 121.14537 | I16: =$C$3*'10'!J19 -> 1211.4537
A17: 11X | B17: =C17/11 -> 125.92682 | C17: =$C$3*'25'!J20 -> 1385.195 | D17: =E17/11 -> 120.88975 | E17: =$C$3*'20'!J20 -> 1329.7872 | F17: =G17/11 -> 115.85268 | G17: =$C$3*'15'!J20 -> 1274.3794 | H17: =I17/11 -> 110.8156 | I17: =$C$3*'10'!J20 -> 1218.9716
A18: 12X | B18: =C18/12 -> 116.76568 | C18: =$C$3*'25'!J21 -> 1401.1882 | D18: =E18/12 -> 112.09506 | E18: =$C$3*'20'!J21 -> 1345.1407 | F18: =G18/12 -> 107.42443 | G18: =$C$3*'15'!J21 -> 1289.0932 | H18: =I18/12 -> 102.7538 | I18: =$C$3*'10'!J21 -> 1233.0456
A19: 13 | C19: 0.0949 | E19: 0.0882 | G19: ='15'!H22 -> 1349.9237 | I19: 0.0759
A20: 14 | C20: 0.0897 | E20: 0.0836 | G20: ='15'!H23 -> 1360.7857 | I20: 0.0708
A21: 15 | C21: 0.0841 | E21: 0.0796 | G21: ='15'!H24 -> 1371.8239 | I21: 0.0667
A22: 16 | C22: 0.0791 | E22: 0.0749 | G22: ='15'!H25 -> 1383.0427 | I22: 0.0628
A23: 17 | C23: 0.0747 | E23: 0.0708 | G23: ='15'!H26 -> 1394.6156 | I23: 0.0596
A24: 18 | C24: 0.0708 | E24: 0.0672 | G24: ='15'!H27 -> 1406.2118 | I24: 0.0564
G25: ='15'!H28 -> 1418.0025

Sheet 10
A1: CUSTO CLIENTE | N1: CUSTO LOJISTA
A4: VALOR DO SERVIÇO | C4: VALOR RECEBIDO (D+1) | H4: GANHO LIQUIDO | O4: VALOR DE SERVIÇO
A5: 1000 | C5: =A5*(1+$K$7) -> 1100 | H5: =IFERROR((C5-(A5)),0) -> 100 | O5: =A5 -> 1000
A7: TIPO DE TRANSAÇÃO | B7: Tabela 8 TB | H7: TABELA REFERENCIA | K7: 0.1 | O7: TIPO DE TRANSAÇÃO | P7: Parcela | Q7: Recebido D+1
B8: Compra | C8: Parcela | D8: CET | E8: Fator | F8: Coeficiente | H8: Compra | I8: Parcela | J8: Fator | K8: Coeficiente
A9: Credito à vista | B9: =($A$5)/(1-D9) -> 1032.2048 | C9: =B9 -> 1032.2048 | D9: 0.0312 | E9: =B9/$A$5 -> 1.0322048 | F9: =C9/A5 -> 1.0322048 | H9: =$A$5*J9 -> 1135.4253 | I9: =H9 -> 1135.4253 | J9: =E9*(1+$K$7) -> 1.1354253 | K9: =I9/$A$5 -> 1.1354253 | O9: Credito à vista | P9: =$O$5 -> 1000 | Q9: =$O$5*(1-D9) -> 968.8
A11: Crédito Parcelado 2x | B11: =$A$5/(1-D11) -> 1044.0593 | C11: =B11/2 -> 522.02965 | D11: 0.0422 | E11: =B11/$A$5 -> 1.0440593 | F11: =C11/$A$5 -> 0.52202965 | H11: =$A$5*J11 -> 1148.4652 | I11: =H11/2 -> 574.23262 | J11: =E11*(1+$K$7) -> 1.1484652 | K11: =I11/$A$5 -> 0.57423262 | O11: Crédito Parcelado 2x | P11: =$O$5/2 -> 500 | Q11: =$O$5*(1-D11) -> 957.8
A12: Crédito Parcelado 3x | B12: =$A$5/(1-D12) -> 1050.7513 | C12: =B12/3 -> 350.25043 | D12: 0.0483 | E12: =B12/$A$5 -> 1.0507513 | F12: =C12/$A$5 -> 0.35025043 | H12: =$A$5*J12 -> 1155.8264 | I12: =H12/3 -> 385.27547 | J12: =E12*(1+$K$7) -> 1.1558264 | K12: =I12/$A$5 -> 0.38527547 | O12: Crédito Parcelado 3x | P12: =$O$5/3 -> 333.33333 | Q12: =$O$5*(1-D12) -> 951.7
A13: Crédito Parcelado 4x | B13: =$A$5/(1-D13) -> 1057.5296 | C13: =B13/4 -> 264.3824 | D13: 0.0544 | E13: =B13/$A$5 -> 1.0575296 | F13: =C13/$A$5 -> 0.2643824 | H13: =$A$5*J13 -> 1163.2826 | I13: =H13/4 -> 290.82064 | J13: =E13*(1+$K$7) -> 1.1632826 | K13: =I13/$A$5 -> 0.29082064 | O13: Crédito Parcelado 4x | P13: =$O$5/4 -> 250 | Q13: =$O$5*(1-D13) -> 945.6
A14: Crédito Parcelado 5x | B14: =$A$5/(1-D14) -> 1064.396 | C14: =B14/5 -> 212.87919 | D14: 0.0605 | E14: =B14/$A$5 -> 1.064396 | F14: =C14/$A$5 -> 0.21287919 | H14: =$A$5*J14 -> 1170.8356 | I14: =H14/5 -> 234.16711 | J14: =E14*(1+$K$7) -> 1.1708356 | K14: =I14/$A$5 -> 0.23416711 | O14: Crédito Parcelado 5x | P14: =$O$5/5 -> 200 | Q14: =$O$5*(1-D14) -> 939.5
A15: Crédito Parcelado 6x | B15: =$A$5/(1-D15) -> 1071.1225 | C15: =B15/6 -> 178.52042 | D15: 0.0664 | E15: =B15/$A$5 -> 1.0711225 | F15: =C15/$A$5 -> 0.17852042 | H15: =$A$5*J15 -> 1178.2348 | I15: =H15/6 -> 196.37247 | J15: =E15*(1+$K$7) -> 1.1782348 | K15: =I15/$A$5 -> 0.19637247 | O15: Crédito Parcelado 6x | P15: =$O$5/6 -> 166.66667 | Q15: =$O$5*(1-D15) -> 933.6
A16: Crédito Parcelado 7x | B16: =$A$5/(1-D16) -> 1078.0509 | C16: =B16/7 -> 154.00727 | D16: 0.0724 | E16: =B16/$A$5 -> 1.0780509 | F16: =C16/$A$5 -> 0.15400727 | H16: =$A$5*J16 -> 1185.856 | I16: =H16/7 -> 169.408 | J16: =E16*(1+$K$7) -> 1.185856 | K16: =I16/$A$5 -> 0.169408 | O16: Crédito Parcelado 7x | P16: =$O$5/7 -> 142.85714 | Q16: =$O$5*(1-D16) -> 927.6
A17: Crédito Parcelado 8x | B17: =$A$5/(1-D17) -> 1084.834 | C17: =B17/8 -> 135.60425 | D17: 0.0782 | E17: =B17/$A$5 -> 1.084834 | F17: =C17/$A$5 -> 0.13560425 | H17: =$A$5*J17 -> 1193.3174 | I17: =H17/8 -> 149.16468 | J17: =E17*(1+$K$7) -> 1.1933174 | K17: =I17/$A$5 -> 0.14916468 | O17: Crédito Parcelado 8x | P17: =$O$5/8 -> 125 | Q17: =$O$5*(1-D17) -> 921.8
A18: Crédito Parcelado 9x | B18: =$A$5/(1-D18) -> 1091.8223 | C18: =B18/9 -> 121.31358 | D18: 0.0841 | E18: =B18/$A$5 -> 1.0918223 | F18: =C18/$A$5 -> 0.12131358 | H18: =$A$5*J18 -> 1201.0045 | I18: =H18/9 -> 133.44494 | J18: =E18*(1+$K$7) -> 1.2010045 | K18: =I18/$A$5 -> 0.13344494 | O18: Crédito Parcelado 9x | P18: =$O$5/9 -> 111.11111 | Q18: =$O$5*(1-D18) -> 915.9
A19: Crédito Parcelado 10x | B19: =$A$5/(1-D19) -> 1101.3216 | C19: =B19/10 -> 110.13216 | D19: 0.092 | E19: =B19/$A$5 -> 1.1013216 | F19: =C19/$A$5 -> 0.11013216 | H19: =$A$5*J19 -> 1211.4537 | I19: =H19/10 -> 121.14537 | J19: =E19*(1+$K$7) -> 1.2114537 | K19: =I19/$A$5 -> 0.12114537 | O19: Crédito Parcelado 10x | P19: =$O$5/10 -> 100 | Q19: =$O$5*(1-D19) -> 908
A20: Crédito Parcelado 11x | B20: =$A$5/(1-D20) -> 1108.156 | C20: =B20/11 -> 100.74146 | D20: 0.0976 | E20: =B20/$A$5 -> 1.108156 | F20: =C20/$A$5 -> 0.10074146 | H20: =$A$5*J20 -> 1218.9716 | I20: =H20/11 -> 110.8156 | J20: =E20*(1+$K$7) -> 1.2189716 | K20: =I20/$A$5 -> 0.1108156 | O20: Crédito Parcelado 11x | P20: =$O$5/11 -> 90.909091 | Q20: =$O$5*(1-D20) -> 902.4
A21: Crédito Parcelado 12x | B21: =$A$5/(1-D21) -> 1120.9506 | C21: =B21/12 -> 93.412547 | D21: 0.1079 | E21: =B21/$A$5 -> 1.1209506 | F21: =C21/$A$5 -> 0.093412547 | H21: =$A$5*J21 -> 1233.0456 | I21: =H21/12 -> 102.7538 | J21: =E21*(1+$K$7) -> 1.2330456 | K21: =I21/$A$5 -> 0.1027538 | O21: Crédito Parcelado 12x | P21: =$O$5/12 -> 83.333333 | Q21: =$O$5*(1-D21) -> 892.1
A22: Crédito Parcelado 13x | B22: =$A$5/(1-D22) -> 1173.8467 | C22: =B22/13 -> 90.2959 | D22: 0.1481 | E22: =B22/$A$5 -> 1.1738467 | F22: =C22/$A$5 -> 0.0902959 | H22: =$A$5*J22 -> 1291.2314 | I22: =H22/13 -> 99.32549 | J22: =E22*(1+$K$7) -> 1.2912314 | K22: =I22/$A$5 -> 0.09932549 | O22: =A22 -> Crédito Parcelado 13x | P22: =$O$5/13 -> 76.923077 | Q22: =$O$5*(1-D22) -> 851.9
A23: Crédito Parcelado 14x | B23: =$A$5/(1-D23) -> 1183.2919 | C23: =B23/14 -> 84.520851 | D23: 0.1549 | E23: =B23/$A$5 -> 1.1832919 | F23: =C23/$A$5 -> 0.084520851 | H23: =$A$5*J23 -> 1301.6211 | I23: =H23/14 -> 92.972936 | J23: =E23*(1+$K$7) -> 1.3016211 | K23: =I23/$A$5 -> 0.092972936 | O23: =A23 -> Crédito Parcelado 14x | P23: =$O$5/14 -> 71.428571 | Q23: =$O$5*(1-D23) -> 845.1
A24: Crédito Parcelado 15x | B24: =$A$5/(1-D24) -> 1192.8904 | C24: =B24/15 -> 79.526025 | D24: 0.1617 | E24: =B24/$A$5 -> 1.1928904 | F24: =C24/$A$5 -> 0.079526025 | H24: =$A$5*J24 -> 1312.1794 | I24: =H24/15 -> 87.478627 | J24: =E24*(1+$K$7) -> 1.3121794 | K24: =I24/$A$5 -> 0.087478627 | O24: =A24 -> Crédito Parcelado 15x | P24: =$O$5/15 -> 66.666667 | Q24: =$O$5*(1-D24) -> 838.3
A25: Crédito Parcelado 16x | B25: =$A$5/(1-D25) -> 1202.6458 | C25: =B25/16 -> 75.165364 | D25: 0.1685 | E25: =B25/$A$5 -> 1.2026458 | F25: =C25/$A$5 -> 0.075165364 | H25: =$A$5*J25 -> 1322.9104 | I25: =H25/16 -> 82.6819 | J25: =E25*(1+$K$7) -> 1.3229104 | K25: =I25/$A$5 -> 0.0826819 | O25: =A25 -> Crédito Parcelado 16x | P25: =$O$5/16 -> 62.5 | Q25: =$O$5*(1-D25) -> 831.5
A26: Crédito Parcelado 17x | B26: =$A$5/(1-D26) -> 1212.7092 | C26: =B26/17 -> 71.335835 | D26: 0.1754 | E26: =B26/$A$5 -> 1.2127092 | F26: =C26/$A$5 -> 0.071335835 | H26: =$A$5*J26 -> 1333.9801 | I26: =H26/17 -> 78.469418 | J26: =E26*(1+$K$7) -> 1.3339801 | K26: =I26/$A$5 -> 0.078469418 | O26: =A26 -> Crédito Parcelado 17x | P26: =$O$5/17 -> 58.823529 | Q26: =$O$5*(1-D26) -> 824.6
A27: Crédito Parcelado 18x | B27: =$A$5/(1-D27) -> 1222.7929 | C27: =B27/18 -> 67.932937 | D27: 0.1822 | E27: =B27/$A$5 -> 1.2227929 | F27: =C27/$A$5 -> 0.067932937 | H27: =$A$5*J27 -> 1345.0721 | I27: =H27/18 -> 74.72623 | J27: =E27*(1+$K$7) -> 1.3450721 | K27: =I27/$A$5 -> 0.07472623 | O27: =A27 -> Crédito Parcelado 18x | P27: =$O$5/18 -> 55.555556 | Q27: =$O$5*(1-D27) -> 817.8
A28: Crédito Parcelado 19 | B28: =$A$5/(1-D28) -> 1233.0456 | C28: =B28/19 -> 64.897138 | D28: 0.189 | E28: =B28/$A$5 -> 1.2330456 | F28: =C28/$A$5 -> 0.064897138 | H28: =$A$5*J28 -> 1356.3502 | I28: =H28/19 -> 71.386852 | J28: =E28*(1+$K$7) -> 1.3563502 | K28: =I28/$A$5 -> 0.071386852 | O28: =A28 -> Crédito Parcelado 19 | P28: =$O$5/19 -> 52.631579 | Q28: =$O$5*(1-D28) -> 811
A29: Crédito Parcelado 20x | B29: =$A$5/(1-D29) -> 1243.4718 | C29: =B29/20 -> 62.173589 | D29: 0.1958 | E29: =B29/$A$5 -> 1.2434718 | F29: =C29/$A$5 -> 0.062173589 | H29: =$A$5*J29 -> 1367.819 | I29: =H29/20 -> 68.390948 | J29: =E29*(1+$K$7) -> 1.367819 | K29: =I29/$A$5 -> 0.068390948 | O29: =A29 -> Crédito Parcelado 20x | P29: =$O$5/20 -> 50 | Q29: =$O$5*(1-D29) -> 804.2
A30: Crédito Parcelado 21x | B30: =$A$5/(1-D30) -> 1254.0757 | C30: =B30/21 -> 59.717893 | D30: 0.2026 | E30: =B30/$A$5 -> 1.2540757 | F30: =C30/$A$5 -> 0.059717893 | H30: =$A$5*J30 -> 1379.4833 | I30: =H30/21 -> 65.689682 | J30: =E30*(1+$K$7) -> 1.3794833 | K30: =I30/$A$5 -> 0.065689682 | O30: =A30 -> Crédito Parcelado 21x | P30: =$O$5/21 -> 47.619048 | Q30: =$O$5*(1-D30) -> 797.4
A32: Débito (Visa/Master) | B32: =$A$5/(1-D32) -> 1009.999 | C32: =B32 -> 1009.999 | D32: 0.0099 | E32: =C32/A5 -> 1.009999 | F32: =C32/A5 -> 1.009999 | H32: 111.56615 | I32: 111.56615 | J32: =E32*(1+$K$7) -> 1.1109989 | K32: 1.1156615 | O32: =A32 -> Débito (Visa/Master) | P32: =O5 -> 1000 | Q32: =$O$5*(1-D32) -> 990.1
A34: Débito (Elo, Hiper e Amex) | B34: =$A$5/(1-D34) -> 1009.999 | C34: =B34 -> 1009.999 | D34: 0.0099 | E34: =C34/A5 -> 1.009999 | F34: =C34/A5 -> 1.009999 | H34: 108.59543 | I34: 108.59543 | J34: =E34*(1+$K$7) -> 1.1109989 | K34: 1.0859543 | O34: =A34 -> Débito (Elo, Hiper e Amex) | P34: =O5 -> 1000 | Q34: =$O$5*(1-D34) -> 990.1

Sheet 15
A1: CUSTO CLIENTE | N1: CUSTO LOJISTA
A4: VALOR DO SERVIÇO | C4: VALOR RECEBIDO (D+1) | H4: GANHO LIQUIDO | O4: VALOR DE SERVIÇO
A5: 1000 | C5: =A5*(1+$K$7) -> 1150 | H5: =IFERROR((C5-(A5)),0) -> 150 | O5: =A5 -> 1000
A7: TIPO DE TRANSAÇÃO | B7: Tabela 8 TB | H7: TABELA REFERENCIA | K7: 0.15 | O7: TIPO DE TRANSAÇÃO | P7: Parcela | Q7: Recebido D+1
B8: Compra | C8: Parcela | D8: CET | E8: Fator | F8: Coeficiente | H8: Compra | I8: Parcela | J8: Fator | K8: Coeficiente
A9: Credito à vista | B9: =($A$5)/(1-D9) -> 1032.2048 | C9: =B9 -> 1032.2048 | D9: 0.0312 | E9: =B9/$A$5 -> 1.0322048 | F9: =C9/A5 -> 1.0322048 | H9: =$A$5*J9 -> 1187.0355 | I9: =H9 -> 1187.0355 | J9: =E9*(1+$K$7) -> 1.1870355 | K9: =I9/$A$5 -> 1.1870355 | O9: Credito à vista | P9: =$O$5 -> 1000 | Q9: =$O$5*(1-D9) -> 968.8
A11: Crédito Parcelado 2x | B11: =$A$5/(1-D11) -> 1044.0593 | C11: =B11/2 -> 522.02965 | D11: 0.0422 | E11: =B11/$A$5 -> 1.0440593 | F11: =C11/$A$5 -> 0.52202965 | H11: =$A$5*J11 -> 1200.6682 | I11: =H11/2 -> 600.3341 | J11: =E11*(1+$K$7) -> 1.2006682 | K11: =I11/$A$5 -> 0.6003341 | O11: Crédito Parcelado 2x | P11: =$O$5/2 -> 500 | Q11: =$O$5*(1-D11) -> 957.8
A12: Crédito Parcelado 3x | B12: =$A$5/(1-D12) -> 1050.7513 | C12: =B12/3 -> 350.25043 | D12: 0.0483 | E12: =B12/$A$5 -> 1.0507513 | F12: =C12/$A$5 -> 0.35025043 | H12: =$A$5*J12 -> 1208.364 | I12: =H12/3 -> 402.78799 | J12: =E12*(1+$K$7) -> 1.208364 | K12: =I12/$A$5 -> 0.40278799 | O12: Crédito Parcelado 3x | P12: =$O$5/3 -> 333.33333 | Q12: =$O$5*(1-D12) -> 951.7
A13: Crédito Parcelado 4x | B13: =$A$5/(1-D13) -> 1057.5296 | C13: =B13/4 -> 264.3824 | D13: 0.0544 | E13: =B13/$A$5 -> 1.0575296 | F13: =C13/$A$5 -> 0.2643824 | H13: =$A$5*J13 -> 1216.1591 | I13: =H13/4 -> 304.03976 | J13: =E13*(1+$K$7) -> 1.2161591 | K13: =I13/$A$5 -> 0.30403976 | O13: Crédito Parcelado 4x | P13: =$O$5/4 -> 250 | Q13: =$O$5*(1-D13) -> 945.6
A14: Crédito Parcelado 5x | B14: =$A$5/(1-D14) -> 1064.396 | C14: =B14/5 -> 212.87919 | D14: 0.0605 | E14: =B14/$A$5 -> 1.064396 | F14: =C14/$A$5 -> 0.21287919 | H14: =$A$5*J14 -> 1224.0553 | I14: =H14/5 -> 244.81107 | J14: =E14*(1+$K$7) -> 1.2240553 | K14: =I14/$A$5 -> 0.24481107 | O14: Crédito Parcelado 5x | P14: =$O$5/5 -> 200 | Q14: =$O$5*(1-D14) -> 939.5
A15: Crédito Parcelado 6x | B15: =$A$5/(1-D15) -> 1071.1225 | C15: =B15/6 -> 178.52042 | D15: 0.0664 | E15: =B15/$A$5 -> 1.0711225 | F15: =C15/$A$5 -> 0.17852042 | H15: =$A$5*J15 -> 1231.7909 | I15: =H15/6 -> 205.29849 | J15: =E15*(1+$K$7) -> 1.2317909 | K15: =I15/$A$5 -> 0.20529849 | O15: Crédito Parcelado 6x | P15: =$O$5/6 -> 166.66667 | Q15: =$O$5*(1-D15) -> 933.6
A16: Crédito Parcelado 7x | B16: =$A$5/(1-D16) -> 1078.0509 | C16: =B16/7 -> 154.00727 | D16: 0.0724 | E16: =B16/$A$5 -> 1.0780509 | F16: =C16/$A$5 -> 0.15400727 | H16: =$A$5*J16 -> 1239.7585 | I16: =H16/7 -> 177.10836 | J16: =E16*(1+$K$7) -> 1.2397585 | K16: =I16/$A$5 -> 0.17710836 | O16: Crédito Parcelado 7x | P16: =$O$5/7 -> 142.85714 | Q16: =$O$5*(1-D16) -> 927.6
A17: Crédito Parcelado 8x | B17: =$A$5/(1-D17) -> 1084.834 | C17: =B17/8 -> 135.60425 | D17: 0.0782 | E17: =B17/$A$5 -> 1.084834 | F17: =C17/$A$5 -> 0.13560425 | H17: =$A$5*J17 -> 1247.5591 | I17: =H17/8 -> 155.94489 | J17: =E17*(1+$K$7) -> 1.2475591 | K17: =I17/$A$5 -> 0.15594489 | O17: Crédito Parcelado 8x | P17: =$O$5/8 -> 125 | Q17: =$O$5*(1-D17) -> 921.8
A18: Crédito Parcelado 9x | B18: =$A$5/(1-D18) -> 1091.8223 | C18: =B18/9 -> 121.31358 | D18: 0.0841 | E18: =B18/$A$5 -> 1.0918223 | F18: =C18/$A$5 -> 0.12131358 | H18: =$A$5*J18 -> 1255.5956 | I18: =H18/9 -> 139.51062 | J18: =E18*(1+$K$7) -> 1.2555956 | K18: =I18/$A$5 -> 0.13951062 | O18: Crédito Parcelado 9x | P18: =$O$5/9 -> 111.11111 | Q18: =$O$5*(1-D18) -> 915.9
A19: Crédito Parcelado 10x | B19: =$A$5/(1-D19) -> 1101.3216 | C19: =B19/10 -> 110.13216 | D19: 0.092 | E19: =B19/$A$5 -> 1.1013216 | F19: =C19/$A$5 -> 0.11013216 | H19: =$A$5*J19 -> 1266.5198 | I19: =H19/10 -> 126.65198 | J19: =E19*(1+$K$7) -> 1.2665198 | K19: =I19/$A$5 -> 0.12665198 | O19: Crédito Parcelado 10x | P19: =$O$5/10 -> 100 | Q19: =$O$5*(1-D19) -> 908
A20: Crédito Parcelado 11x | B20: =$A$5/(1-D20) -> 1108.156 | C20: =B20/11 -> 100.74146 | D20: 0.0976 | E20: =B20/$A$5 -> 1.108156 | F20: =C20/$A$5 -> 0.10074146 | H20: =$A$5*J20 -> 1274.3794 | I20: =H20/11 -> 115.85268 | J20: =E20*(1+$K$7) -> 1.2743794 | K20: =I20/$A$5 -> 0.11585268 | O20: Crédito Parcelado 11x | P20: =$O$5/11 -> 90.909091 | Q20: =$O$5*(1-D20) -> 902.4
A21: Crédito Parcelado 12x | B21: =$A$5/(1-D21) -> 1120.9506 | C21: =B21/12 -> 93.412547 | D21: 0.1079 | E21: =B21/$A$5 -> 1.1209506 | F21: =C21/$A$5 -> 0.093412547 | H21: =$A$5*J21 -> 1289.0932 | I21: =H21/12 -> 107.42443 | J21: =E21*(1+$K$7) -> 1.2890932 | K21: =I21/$A$5 -> 0.10742443 | O21: Crédito Parcelado 12x | P21: =$O$5/12 -> 83.333333 | Q21: =$O$5*(1-D21) -> 892.1
A22: Crédito Parcelado 13x | B22: =$A$5/(1-D22) -> 1173.8467 | C22: =B22/13 -> 90.2959 | D22: 0.1481 | E22: =B22/$A$5 -> 1.1738467 | F22: =C22/$A$5 -> 0.0902959 | H22: =$A$5*J22 -> 1349.9237 | I22: =H22/13 -> 103.84028 | J22: =E22*(1+$K$7) -> 1.3499237 | K22: =I22/$A$5 -> 0.10384028 | O22: =A22 -> Crédito Parcelado 13x | P22: =$O$5/13 -> 76.923077 | Q22: =$O$5*(1-D22) -> 851.9
A23: Crédito Parcelado 14x | B23: =$A$5/(1-D23) -> 1183.2919 | C23: =B23/14 -> 84.520851 | D23: 0.1549 | E23: =B23/$A$5 -> 1.1832919 | F23: =C23/$A$5 -> 0.084520851 | H23: =$A$5*J23 -> 1360.7857 | I23: =H23/14 -> 97.198979 | J23: =E23*(1+$K$7) -> 1.3607857 | K23: =I23/$A$5 -> 0.097198979 | O23: =A23 -> Crédito Parcelado 14x | P23: =$O$5/14 -> 71.428571 | Q23: =$O$5*(1-D23) -> 845.1
A24: Crédito Parcelado 15x | B24: =$A$5/(1-D24) -> 1192.8904 | C24: =B24/15 -> 79.526025 | D24: 0.1617 | E24: =B24/$A$5 -> 1.1928904 | F24: =C24/$A$5 -> 0.079526025 | H24: =$A$5*J24 -> 1371.8239 | I24: =H24/15 -> 91.454929 | J24: =E24*(1+$K$7) -> 1.3718239 | K24: =I24/$A$5 -> 0.091454929 | O24: =A24 -> Crédito Parcelado 15x | P24: =$O$5/15 -> 66.666667 | Q24: =$O$5*(1-D24) -> 838.3
A25: Crédito Parcelado 16x | B25: =$A$5/(1-D25) -> 1202.6458 | C25: =B25/16 -> 75.165364 | D25: 0.1685 | E25: =B25/$A$5 -> 1.2026458 | F25: =C25/$A$5 -> 0.075165364 | H25: =$A$5*J25 -> 1383.0427 | I25: =H25/16 -> 86.440168 | J25: =E25*(1+$K$7) -> 1.3830427 | K25: =I25/$A$5 -> 0.086440168 | O25: =A25 -> Crédito Parcelado 16x | P25: =$O$5/16 -> 62.5 | Q25: =$O$5*(1-D25) -> 831.5
A26: Crédito Parcelado 17x | B26: =$A$5/(1-D26) -> 1212.7092 | C26: =B26/17 -> 71.335835 | D26: 0.1754 | E26: =B26/$A$5 -> 1.2127092 | F26: =C26/$A$5 -> 0.071335835 | H26: =$A$5*J26 -> 1394.6156 | I26: =H26/17 -> 82.03621 | J26: =E26*(1+$K$7) -> 1.3946156 | K26: =I26/$A$5 -> 0.08203621 | O26: =A26 -> Crédito Parcelado 17x | P26: =$O$5/17 -> 58.823529 | Q26: =$O$5*(1-D26) -> 824.6
A27: Crédito Parcelado 18x | B27: =$A$5/(1-D27) -> 1222.7929 | C27: =B27/18 -> 67.932937 | D27: 0.1822 | E27: =B27/$A$5 -> 1.2227929 | F27: =C27/$A$5 -> 0.067932937 | H27: =$A$5*J27 -> 1406.2118 | I27: =H27/18 -> 78.122877 | J27: =E27*(1+$K$7) -> 1.4062118 | K27: =I27/$A$5 -> 0.078122877 | O27: =A27 -> Crédito Parcelado 18x | P27: =$O$5/18 -> 55.555556 | Q27: =$O$5*(1-D27) -> 817.8
A28: Crédito Parcelado 19 | B28: =$A$5/(1-D28) -> 1233.0456 | C28: =B28/19 -> 64.897138 | D28: 0.189 | E28: =B28/$A$5 -> 1.2330456 | F28: =C28/$A$5 -> 0.064897138 | H28: =$A$5*J28 -> 1418.0025 | I28: =H28/19 -> 74.631709 | J28: =E28*(1+$K$7) -> 1.4180025 | K28: =I28/$A$5 -> 0.074631709 | O28: =A28 -> Crédito Parcelado 19 | P28: =$O$5/19 -> 52.631579 | Q28: =$O$5*(1-D28) -> 811
A29: Crédito Parcelado 20x | B29: =$A$5/(1-D29) -> 1243.4718 | C29: =B29/20 -> 62.173589 | D29: 0.1958 | E29: =B29/$A$5 -> 1.2434718 | F29: =C29/$A$5 -> 0.062173589 | H29: =$A$5*J29 -> 1429.9925 | I29: =H29/20 -> 71.499627 | J29: =E29*(1+$K$7) -> 1.4299925 | K29: =I29/$A$5 -> 0.071499627 | O29: =A29 -> Crédito Parcelado 20x | P29: =$O$5/20 -> 50 | Q29: =$O$5*(1-D29) -> 804.2
A30: Crédito Parcelado 21x | B30: =$A$5/(1-D30) -> 1254.0757 | C30: =B30/21 -> 59.717893 | D30: 0.2026 | E30: =B30/$A$5 -> 1.2540757 | F30: =C30/$A$5 -> 0.059717893 | H30: =$A$5*J30 -> 1442.1871 | I30: =H30/21 -> 68.675577 | J30: =E30*(1+$K$7) -> 1.4421871 | K30: =I30/$A$5 -> 0.068675577 | O30: =A30 -> Crédito Parcelado 21x | P30: =$O$5/21 -> 47.619048 | Q30: =$O$5*(1-D30) -> 797.4
A32: Débito (Visa/Master) | B32: =$A$5/(1-D32) -> 1009.999 | C32: =B32 -> 1009.999 | D32: 0.0099 | E32: =C32/A5 -> 1.009999 | F32: =C32/A5 -> 1.009999 | H32: 111.56615 | I32: 111.56615 | J32: =E32*(1+$K$7) -> 1.1614988 | K32: 1.1156615 | O32: =A32 -> Débito (Visa/Master) | P32: =O5 -> 1000 | Q32: =$O$5*(1-D32) -> 990.1
A34: Débito (Elo, Hiper e Amex) | B34: =$A$5/(1-D34) -> 1009.999 | C34: =B34 -> 1009.999 | D34: 0.0099 | E34: =C34/A5 -> 1.009999 | F34: =C34/A5 -> 1.009999 | H34: 108.59543 | I34: 108.59543 | J34: =E34*(1+$K$7) -> 1.1614988 | K34: 1.0859543 | O34: =A34 -> Débito (Elo, Hiper e Amex) | P34: =O5 -> 1000 | Q34: =$O$5*(1-D34) -> 990.1

Sheet 20
A1: CUSTO CLIENTE | N1: CUSTO LOJISTA
A4: VALOR DO SERVIÇO | C4: VALOR RECEBIDO (D+1) | H4: GANHO LIQUIDO | O4: VALOR DE SERVIÇO
A5: 1000 | C5: =A5*(1+$K$7) -> 1200 | H5: =IFERROR((C5-(A5)),0) -> 200 | O5: =A5 -> 1000
A7: TIPO DE TRANSAÇÃO | B7: Tabela 8 TB | H7: TABELA REFERENCIA | K7: 0.2 | O7: TIPO DE TRANSAÇÃO | P7: Parcela | Q7: Recebido D+1
B8: Compra | C8: Parcela | D8: CET | E8: Fator | F8: Coeficiente | H8: Compra | I8: Parcela | J8: Fator | K8: Coeficiente
A9: Credito à vista | B9: =($A$5)/(1-D9) -> 1032.2048 | C9: =B9 -> 1032.2048 | D9: 0.0312 | E9: =B9/$A$5 -> 1.0322048 | F9: =C9/A5 -> 1.0322048 | H9: =$A$5*J9 -> 1238.6457 | I9: =H9 -> 1238.6457 | J9: =E9*(1+$K$7) -> 1.2386457 | K9: =I9/$A$5 -> 1.2386457 | O9: Credito à vista | P9: =$O$5 -> 1000 | Q9: =$O$5*(1-D9) -> 968.8
A11: Crédito Parcelado 2x | B11: =$A$5/(1-D11) -> 1044.0593 | C11: =B11/2 -> 522.02965 | D11: 0.0422 | E11: =B11/$A$5 -> 1.0440593 | F11: =C11/$A$5 -> 0.52202965 | H11: =$A$5*J11 -> 1252.8712 | I11: =H11/2 -> 626.43558 | J11: =E11*(1+$K$7) -> 1.2528712 | K11: =I11/$A$5 -> 0.62643558 | O11: Crédito Parcelado 2x | P11: =$O$5/2 -> 500 | Q11: =$O$5*(1-D11) -> 957.8
A12: Crédito Parcelado 3x | B12: =$A$5/(1-D12) -> 1050.7513 | C12: =B12/3 -> 350.25043 | D12: 0.0483 | E12: =B12/$A$5 -> 1.0507513 | F12: =C12/$A$5 -> 0.35025043 | H12: =$A$5*J12 -> 1260.9015 | I12: =H12/3 -> 420.30051 | J12: =E12*(1+$K$7) -> 1.2609015 | K12: =I12/$A$5 -> 0.42030051 | O12: Crédito Parcelado 3x | P12: =$O$5/3 -> 333.33333 | Q12: =$O$5*(1-D12) -> 951.7
A13: Crédito Parcelado 4x | B13: =$A$5/(1-D13) -> 1057.5296 | C13: =B13/4 -> 264.3824 | D13: 0.0544 | E13: =B13/$A$5 -> 1.0575296 | F13: =C13/$A$5 -> 0.2643824 | H13: =$A$5*J13 -> 1269.0355 | I13: =H13/4 -> 317.25888 | J13: =E13*(1+$K$7) -> 1.2690355 | K13: =I13/$A$5 -> 0.31725888 | O13: Crédito Parcelado 4x | P13: =$O$5/4 -> 250 | Q13: =$O$5*(1-D13) -> 945.6
A14: Crédito Parcelado 5x | B14: =$A$5/(1-D14) -> 1064.396 | C14: =B14/5 -> 212.87919 | D14: 0.0605 | E14: =B14/$A$5 -> 1.064396 | F14: =C14/$A$5 -> 0.21287919 | H14: =$A$5*J14 -> 1277.2751 | I14: =H14/5 -> 255.45503 | J14: =E14*(1+$K$7) -> 1.2772751 | K14: =I14/$A$5 -> 0.25545503 | O14: Crédito Parcelado 5x | P14: =$O$5/5 -> 200 | Q14: =$O$5*(1-D14) -> 939.5
A15: Crédito Parcelado 6x | B15: =$A$5/(1-D15) -> 1071.1225 | C15: =B15/6 -> 178.52042 | D15: 0.0664 | E15: =B15/$A$5 -> 1.0711225 | F15: =C15/$A$5 -> 0.17852042 | H15: =$A$5*J15 -> 1285.347 | I15: =H15/6 -> 214.22451 | J15: =E15*(1+$K$7) -> 1.285347 | K15: =I15/$A$5 -> 0.21422451 | O15: Crédito Parcelado 6x | P15: =$O$5/6 -> 166.66667 | Q15: =$O$5*(1-D15) -> 933.6
A16: Crédito Parcelado 7x | B16: =$A$5/(1-D16) -> 1078.0509 | C16: =B16/7 -> 154.00727 | D16: 0.0724 | E16: =B16/$A$5 -> 1.0780509 | F16: =C16/$A$5 -> 0.15400727 | H16: =$A$5*J16 -> 1293.6611 | I16: =H16/7 -> 184.80872 | J16: =E16*(1+$K$7) -> 1.2936611 | K16: =I16/$A$5 -> 0.18480872 | O16: Crédito Parcelado 7x | P16: =$O$5/7 -> 142.85714 | Q16: =$O$5*(1-D16) -> 927.6
A17: Crédito Parcelado 8x | B17: =$A$5/(1-D17) -> 1084.834 | C17: =B17/8 -> 135.60425 | D17: 0.0782 | E17: =B17/$A$5 -> 1.084834 | F17: =C17/$A$5 -> 0.13560425 | H17: =$A$5*J17 -> 1301.8008 | I17: =H17/8 -> 162.7251 | J17: =E17*(1+$K$7) -> 1.3018008 | K17: =I17/$A$5 -> 0.1627251 | O17: Crédito Parcelado 8x | P17: =$O$5/8 -> 125 | Q17: =$O$5*(1-D17) -> 921.8
A18: Crédito Parcelado 9x | B18: =$A$5/(1-D18) -> 1091.8223 | C18: =B18/9 -> 121.31358 | D18: 0.0841 | E18: =B18/$A$5 -> 1.0918223 | F18: =C18/$A$5 -> 0.12131358 | H18: =$A$5*J18 -> 1310.1867 | I18: =H18/9 -> 145.5763 | J18: =E18*(1+$K$7) -> 1.3101867 | K18: =I18/$A$5 -> 0.1455763 | O18: Crédito Parcelado 9x | P18: =$O$5/9 -> 111.11111 | Q18: =$O$5*(1-D18) -> 915.9
A19: Crédito Parcelado 10x | B19: =$A$5/(1-D19) -> 1101.3216 | C19: =B19/10 -> 110.13216 | D19: 0.092 | E19: =B19/$A$5 -> 1.1013216 | F19: =C19/$A$5 -> 0.11013216 | H19: =$A$5*J19 -> 1321.5859 | I19: =H19/10 -> 132.15859 | J19: =E19*(1+$K$7) -> 1.3215859 | K19: =I19/$A$5 -> 0.13215859 | O19: Crédito Parcelado 10x | P19: =$O$5/10 -> 100 | Q19: =$O$5*(1-D19) -> 908
A20: Crédito Parcelado 11x | B20: =$A$5/(1-D20) -> 1108.156 | C20: =B20/11 -> 100.74146 | D20: 0.0976 | E20: =B20/$A$5 -> 1.108156 | F20: =C20/$A$5 -> 0.10074146 | H20: =$A$5*J20 -> 1329.7872 | I20: =H20/11 -> 120.88975 | J20: =E20*(1+$K$7) -> 1.3297872 | K20: =I20/$A$5 -> 0.12088975 | O20: Crédito Parcelado 11x | P20: =$O$5/11 -> 90.909091 | Q20: =$O$5*(1-D20) -> 902.4
A21: Crédito Parcelado 12x | B21: =$A$5/(1-D21) -> 1120.9506 | C21: =B21/12 -> 93.412547 | D21: 0.1079 | E21: =B21/$A$5 -> 1.1209506 | F21: =C21/$A$5 -> 0.093412547 | H21: =$A$5*J21 -> 1345.1407 | I21: =H21/12 -> 112.09506 | J21: =E21*(1+$K$7) -> 1.3451407 | K21: =I21/$A$5 -> 0.11209506 | O21: Crédito Parcelado 12x | P21: =$O$5/12 -> 83.333333 | Q21: =$O$5*(1-D21) -> 892.1
A22: Crédito Parcelado 13x | B22: =$A$5/(1-D22) -> 1173.8467 | C22: =B22/13 -> 90.2959 | D22: 0.1481 | E22: =B22/$A$5 -> 1.1738467 | F22: =C22/$A$5 -> 0.0902959 | H22: =$A$5*J22 -> 1408.616 | I22: =H22/13 -> 108.35508 | J22: =E22*(1+$K$7) -> 1.408616 | K22: =I22/$A$5 -> 0.10835508 | O22: =A22 -> Crédito Parcelado 13x | P22: =$O$5/13 -> 76.923077 | Q22: =$O$5*(1-D22) -> 851.9
A23: Crédito Parcelado 14x | B23: =$A$5/(1-D23) -> 1183.2919 | C23: =B23/14 -> 84.520851 | D23: 0.1549 | E23: =B23/$A$5 -> 1.1832919 | F23: =C23/$A$5 -> 0.084520851 | H23: =$A$5*J23 -> 1419.9503 | I23: =H23/14 -> 101.42502 | J23: =E23*(1+$K$7) -> 1.4199503 | K23: =I23/$A$5 -> 0.10142502 | O23: =A23 -> Crédito Parcelado 14x | P23: =$O$5/14 -> 71.428571 | Q23: =$O$5*(1-D23) -> 845.1
A24: Crédito Parcelado 15x | B24: =$A$5/(1-D24) -> 1192.8904 | C24: =B24/15 -> 79.526025 | D24: 0.1617 | E24: =B24/$A$5 -> 1.1928904 | F24: =C24/$A$5 -> 0.079526025 | H24: =$A$5*J24 -> 1431.4684 | I24: =H24/15 -> 95.43123 | J24: =E24*(1+$K$7) -> 1.4314684 | K24: =I24/$A$5 -> 0.09543123 | O24: =A24 -> Crédito Parcelado 15x | P24: =$O$5/15 -> 66.666667 | Q24: =$O$5*(1-D24) -> 838.3
A25: Crédito Parcelado 16x | B25: =$A$5/(1-D25) -> 1202.6458 | C25: =B25/16 -> 75.165364 | D25: 0.1685 | E25: =B25/$A$5 -> 1.2026458 | F25: =C25/$A$5 -> 0.075165364 | H25: =$A$5*J25 -> 1443.175 | I25: =H25/16 -> 90.198437 | J25: =E25*(1+$K$7) -> 1.443175 | K25: =I25/$A$5 -> 0.090198437 | O25: =A25 -> Crédito Parcelado 16x | P25: =$O$5/16 -> 62.5 | Q25: =$O$5*(1-D25) -> 831.5
A26: Crédito Parcelado 17x | B26: =$A$5/(1-D26) -> 1212.7092 | C26: =B26/17 -> 71.335835 | D26: 0.1754 | E26: =B26/$A$5 -> 1.2127092 | F26: =C26/$A$5 -> 0.071335835 | H26: =$A$5*J26 -> 1455.251 | I26: =H26/17 -> 85.603002 | J26: =E26*(1+$K$7) -> 1.455251 | K26: =I26/$A$5 -> 0.085603002 | O26: =A26 -> Crédito Parcelado 17x | P26: =$O$5/17 -> 58.823529 | Q26: =$O$5*(1-D26) -> 824.6
A27: Crédito Parcelado 18x | B27: =$A$5/(1-D27) -> 1222.7929 | C27: =B27/18 -> 67.932937 | D27: 0.1822 | E27: =B27/$A$5 -> 1.2227929 | F27: =C27/$A$5 -> 0.067932937 | H27: =$A$5*J27 -> 1467.3514 | I27: =H27/18 -> 81.519524 | J27: =E27*(1+$K$7) -> 1.4673514 | K27: =I27/$A$5 -> 0.081519524 | O27: =A27 -> Crédito Parcelado 18x | P27: =$O$5/18 -> 55.555556 | Q27: =$O$5*(1-D27) -> 817.8
A28: Crédito Parcelado 19 | B28: =$A$5/(1-D28) -> 1233.0456 | C28: =B28/19 -> 64.897138 | D28: 0.189 | E28: =B28/$A$5 -> 1.2330456 | F28: =C28/$A$5 -> 0.064897138 | H28: =$A$5*J28 -> 1479.6547 | I28: =H28/19 -> 77.876566 | J28: =E28*(1+$K$7) -> 1.4796547 | K28: =I28/$A$5 -> 0.077876566 | O28: =A28 -> Crédito Parcelado 19 | P28: =$O$5/19 -> 52.631579 | Q28: =$O$5*(1-D28) -> 811
A29: Crédito Parcelado 20x | B29: =$A$5/(1-D29) -> 1243.4718 | C29: =B29/20 -> 62.173589 | D29: 0.1958 | E29: =B29/$A$5 -> 1.2434718 | F29: =C29/$A$5 -> 0.062173589 | H29: =$A$5*J29 -> 1492.1661 | I29: =H29/20 -> 74.608306 | J29: =E29*(1+$K$7) -> 1.4921661 | K29: =I29/$A$5 -> 0.074608306 | O29: =A29 -> Crédito Parcelado 20x | P29: =$O$5/20 -> 50 | Q29: =$O$5*(1-D29) -> 804.2
A30: Crédito Parcelado 21x | B30: =$A$5/(1-D30) -> 1254.0757 | C30: =B30/21 -> 59.717893 | D30: 0.2026 | E30: =B30/$A$5 -> 1.2540757 | F30: =C30/$A$5 -> 0.059717893 | H30: =$A$5*J30 -> 1504.8909 | I30: =H30/21 -> 71.661471 | J30: =E30*(1+$K$7) -> 1.5048909 | K30: =I30/$A$5 -> 0.071661471 | O30: =A30 -> Crédito Parcelado 21x | P30: =$O$5/21 -> 47.619048 | Q30: =$O$5*(1-D30) -> 797.4
A32: Débito (Visa/Master) | B32: =$A$5/(1-D32) -> 1009.999 | C32: =B32 -> 1009.999 | D32: 0.0099 | E32: =C32/A5 -> 1.009999 | F32: =C32/A5 -> 1.009999 | H32: 111.56615 | I32: 111.56615 | J32: =E32*(1+$K$7) -> 1.2119988 | K32: 1.1156615 | O32: =A32 -> Débito (Visa/Master) | P32: =O5 -> 1000 | Q32: =$O$5*(1-D32) -> 990.1
A34: Débito (Elo, Hiper e Amex) | B34: =$A$5/(1-D34) -> 1009.999 | C34: =B34 -> 1009.999 | D34: 0.0099 | E34: =C34/A5 -> 1.009999 | F34: =C34/A5 -> 1.009999 | H34: 108.59543 | I34: 108.59543 | J34: =E34*(1+$K$7) -> 1.2119988 | K34: 1.0859543 | O34: =A34 -> Débito (Elo, Hiper e Amex) | P34: =O5 -> 1000 | Q34: =$O$5*(1-D34) -> 990.1

Sheet 25
A1: CUSTO CLIENTE | N1: CUSTO LOJISTA
A4: VALOR DO SERVIÇO | C4: VALOR RECEBIDO (D+1) | H4: GANHO LIQUIDO | O4: VALOR DE SERVIÇO
A5: 1000 | C5: =A5*(1+$K$7) -> 1250 | H5: =IFERROR((C5-(A5)),0) -> 250 | O5: =A5 -> 1000
A7: TIPO DE TRANSAÇÃO | B7: Tabela 8 TB | H7: TABELA REFERENCIA | K7: 0.25 | O7: TIPO DE TRANSAÇÃO | P7: Parcela | Q7: Recebido D+1
B8: Compra | C8: Parcela | D8: CET | E8: Fator | F8: Coeficiente | H8: Compra | I8: Parcela | J8: Fator | K8: Coeficiente
A9: Credito à vista | B9: =($A$5)/(1-D9) -> 1032.2048 | C9: =B9 -> 1032.2048 | D9: 0.0312 | E9: =B9/$A$5 -> 1.0322048 | F9: =C9/A5 -> 1.0322048 | H9: =$A$5*J9 -> 1290.256 | I9: =H9 -> 1290.256 | J9: =E9*(1+$K$7) -> 1.290256 | K9: =I9/$A$5 -> 1.290256 | O9: Credito à vista | P9: =$O$5 -> 1000 | Q9: =$O$5*(1-D9) -> 968.8
A11: Crédito Parcelado 2x | B11: =$A$5/(1-D11) -> 1044.0593 | C11: =B11/2 -> 522.02965 | D11: 0.0422 | E11: =B11/$A$5 -> 1.0440593 | F11: =C11/$A$5 -> 0.52202965 | H11: =$A$5*J11 -> 1305.0741 | I11: =H11/2 -> 652.53706 | J11: =E11*(1+$K$7) -> 1.3050741 | K11: =I11/$A$5 -> 0.65253706 | O11: Crédito Parcelado 2x | P11: =$O$5/2 -> 500 | Q11: =$O$5*(1-D11) -> 957.8
A12: Crédito Parcelado 3x | B12: =$A$5/(1-D12) -> 1050.7513 | C12: =B12/3 -> 350.25043 | D12: 0.0483 | E12: =B12/$A$5 -> 1.0507513 | F12: =C12/$A$5 -> 0.35025043 | H12: =$A$5*J12 -> 1313.4391 | I12: =H12/3 -> 437.81304 | J12: =E12*(1+$K$7) -> 1.3134391 | K12: =I12/$A$5 -> 0.43781304 | O12: Crédito Parcelado 3x | P12: =$O$5/3 -> 333.33333 | Q12: =$O$5*(1-D12) -> 951.7 | Y12: R
A13: Crédito Parcelado 4x | B13: =$A$5/(1-D13) -> 1057.5296 | C13: =B13/4 -> 264.3824 | D13: 0.0544 | E13: =B13/$A$5 -> 1.0575296 | F13: =C13/$A$5 -> 0.2643824 | H13: =$A$5*J13 -> 1321.912 | I13: =H13/4 -> 330.478 | J13: =E13*(1+$K$7) -> 1.321912 | K13: =I13/$A$5 -> 0.330478 | O13: Crédito Parcelado 4x | P13: =$O$5/4 -> 250 | Q13: =$O$5*(1-D13) -> 945.6
A14: Crédito Parcelado 5x | B14: =$A$5/(1-D14) -> 1064.396 | C14: =B14/5 -> 212.87919 | D14: 0.0605 | E14: =B14/$A$5 -> 1.064396 | F14: =C14/$A$5 -> 0.21287919 | H14: =$A$5*J14 -> 1330.4949 | I14: =H14/5 -> 266.09899 | J14: =E14*(1+$K$7) -> 1.3304949 | K14: =I14/$A$5 -> 0.26609899 | O14: Crédito Parcelado 5x | P14: =$O$5/5 -> 200 | Q14: =$O$5*(1-D14) -> 939.5
A15: Crédito Parcelado 6x | B15: =$A$5/(1-D15) -> 1071.1225 | C15: =B15/6 -> 178.52042 | D15: 0.0664 | E15: =B15/$A$5 -> 1.0711225 | F15: =C15/$A$5 -> 0.17852042 | H15: =$A$5*J15 -> 1338.9032 | I15: =H15/6 -> 223.15053 | J15: =E15*(1+$K$7) -> 1.3389032 | K15: =I15/$A$5 -> 0.22315053 | O15: Crédito Parcelado 6x | P15: =$O$5/6 -> 166.66667 | Q15: =$O$5*(1-D15) -> 933.6
A16: Crédito Parcelado 7x | B16: =$A$5/(1-D16) -> 1078.0509 | C16: =B16/7 -> 154.00727 | D16: 0.0724 | E16: =B16/$A$5 -> 1.0780509 | F16: =C16/$A$5 -> 0.15400727 | H16: =$A$5*J16 -> 1347.5636 | I16: =H16/7 -> 192.50909 | J16: =E16*(1+$K$7) -> 1.3475636 | K16: =I16/$A$5 -> 0.19250909 | O16: Crédito Parcelado 7x | P16: =$O$5/7 -> 142.85714 | Q16: =$O$5*(1-D16) -> 927.6
A17: Crédito Parcelado 8x | B17: =$A$5/(1-D17) -> 1084.834 | C17: =B17/8 -> 135.60425 | D17: 0.0782 | E17: =B17/$A$5 -> 1.084834 | F17: =C17/$A$5 -> 0.13560425 | H17: =$A$5*J17 -> 1356.0425 | I17: =H17/8 -> 169.50532 | J17: =E17*(1+$K$7) -> 1.3560425 | K17: =I17/$A$5 -> 0.16950532 | O17: Crédito Parcelado 8x | P17: =$O$5/8 -> 125 | Q17: =$O$5*(1-D17) -> 921.8
A18: Crédito Parcelado 9x | B18: =$A$5/(1-D18) -> 1091.8223 | C18: =B18/9 -> 121.31358 | D18: 0.0841 | E18: =B18/$A$5 -> 1.0918223 | F18: =C18/$A$5 -> 0.12131358 | H18: =$A$5*J18 -> 1364.7778 | I18: =H18/9 -> 151.64198 | J18: =E18*(1+$K$7) -> 1.3647778 | K18: =I18/$A$5 -> 0.15164198 | O18: Crédito Parcelado 9x | P18: =$O$5/9 -> 111.11111 | Q18: =$O$5*(1-D18) -> 915.9
A19: Crédito Parcelado 10x | B19: =$A$5/(1-D19) -> 1101.3216 | C19: =B19/10 -> 110.13216 | D19: 0.092 | E19: =B19/$A$5 -> 1.1013216 | F19: =C19/$A$5 -> 0.11013216 | H19: =$A$5*J19 -> 1376.652 | I19: =H19/10 -> 137.6652 | J19: =E19*(1+$K$7) -> 1.376652 | K19: =I19/$A$5 -> 0.1376652 | O19: Crédito Parcelado 10x | P19: =$O$5/10 -> 100 | Q19: =$O$5*(1-D19) -> 908
A20: Crédito Parcelado 11x | B20: =$A$5/(1-D20) -> 1108.156 | C20: =B20/11 -> 100.74146 | D20: 0.0976 | E20: =B20/$A$5 -> 1.108156 | F20: =C20/$A$5 -> 0.10074146 | H20: =$A$5*J20 -> 1385.195 | I20: =H20/11 -> 125.92682 | J20: =E20*(1+$K$7) -> 1.385195 | K20: =I20/$A$5 -> 0.12592682 | O20: Crédito Parcelado 11x | P20: =$O$5/11 -> 90.909091 | Q20: =$O$5*(1-D20) -> 902.4
A21: Crédito Parcelado 12x | B21: =$A$5/(1-D21) -> 1120.9506 | C21: =B21/12 -> 93.412547 | D21: 0.1079 | E21: =B21/$A$5 -> 1.1209506 | F21: =C21/$A$5 -> 0.093412547 | H21: =$A$5*J21 -> 1401.1882 | I21: =H21/12 -> 116.76568 | J21: =E21*(1+$K$7) -> 1.4011882 | K21: =I21/$A$5 -> 0.11676568 | O21: Crédito Parcelado 12x | P21: =$O$5/12 -> 83.333333 | Q21: =$O$5*(1-D21) -> 892.1
A22: Crédito Parcelado 13x | B22: =$A$5/(1-D22) -> 1173.8467 | C22: =B22/13 -> 90.2959 | D22: 0.1481 | E22: =B22/$A$5 -> 1.1738467 | F22: =C22/$A$5 -> 0.0902959 | H22: =$A$5*J22 -> 1467.3084 | I22: =H22/13 -> 112.86987 | J22: =E22*(1+$K$7) -> 1.4673084 | K22: =I22/$A$5 -> 0.11286987 | O22: =A22 -> Crédito Parcelado 13x | P22: =$O$5/13 -> 76.923077 | Q22: =$O$5*(1-D22) -> 851.9
A23: Crédito Parcelado 14x | B23: =$A$5/(1-D23) -> 1183.2919 | C23: =B23/14 -> 84.520851 | D23: 0.1549 | E23: =B23/$A$5 -> 1.1832919 | F23: =C23/$A$5 -> 0.084520851 | H23: =$A$5*J23 -> 1479.1149 | I23: =H23/14 -> 105.65106 | J23: =E23*(1+$K$7) -> 1.4791149 | K23: =I23/$A$5 -> 0.10565106 | O23: =A23 -> Crédito Parcelado 14x | P23: =$O$5/14 -> 71.428571 | Q23: =$O$5*(1-D23) -> 845.1
A24: Crédito Parcelado 15x | B24: =$A$5/(1-D24) -> 1192.8904 | C24: =B24/15 -> 79.526025 | D24: 0.1617 | E24: =B24/$A$5 -> 1.1928904 | F24: =C24/$A$5 -> 0.079526025 | H24: =$A$5*J24 -> 1491.113 | I24: =H24/15 -> 99.407531 | J24: =E24*(1+$K$7) -> 1.491113 | K24: =I24/$A$5 -> 0.099407531 | O24: =A24 -> Crédito Parcelado 15x | P24: =$O$5/15 -> 66.666667 | Q24: =$O$5*(1-D24) -> 838.3
A25: Crédito Parcelado 16x | B25: =$A$5/(1-D25) -> 1202.6458 | C25: =B25/16 -> 75.165364 | D25: 0.1685 | E25: =B25/$A$5 -> 1.2026458 | F25: =C25/$A$5 -> 0.075165364 | H25: =$A$5*J25 -> 1503.3073 | I25: =H25/16 -> 93.956705 | J25: =E25*(1+$K$7) -> 1.5033073 | K25: =I25/$A$5 -> 0.093956705 | O25: =A25 -> Crédito Parcelado 16x | P25: =$O$5/16 -> 62.5 | Q25: =$O$5*(1-D25) -> 831.5
A26: Crédito Parcelado 17x | B26: =$A$5/(1-D26) -> 1212.7092 | C26: =B26/17 -> 71.335835 | D26: 0.1754 | E26: =B26/$A$5 -> 1.2127092 | F26: =C26/$A$5 -> 0.071335835 | H26: =$A$5*J26 -> 1515.8865 | I26: =H26/17 -> 89.169794 | J26: =E26*(1+$K$7) -> 1.5158865 | K26: =I26/$A$5 -> 0.089169794 | O26: =A26 -> Crédito Parcelado 17x | P26: =$O$5/17 -> 58.823529 | Q26: =$O$5*(1-D26) -> 824.6
A27: Crédito Parcelado 18x | B27: =$A$5/(1-D27) -> 1222.7929 | C27: =B27/18 -> 67.932937 | D27: 0.1822 | E27: =B27/$A$5 -> 1.2227929 | F27: =C27/$A$5 -> 0.067932937 | H27: =$A$5*J27 -> 1528.4911 | I27: =H27/18 -> 84.916171 | J27: =E27*(1+$K$7) -> 1.5284911 | K27: =I27/$A$5 -> 0.084916171 | O27: =A27 -> Crédito Parcelado 18x | P27: =$O$5/18 -> 55.555556 | Q27: =$O$5*(1-D27) -> 817.8
A28: Crédito Parcelado 19 | B28: =$A$5/(1-D28) -> 1233.0456 | C28: =B28/19 -> 64.897138 | D28: 0.189 | E28: =B28/$A$5 -> 1.2330456 | F28: =C28/$A$5 -> 0.064897138 | H28: =$A$5*J28 -> 1541.307 | I28: =H28/19 -> 81.121423 | J28: =E28*(1+$K$7) -> 1.541307 | K28: =I28/$A$5 -> 0.081121423 | O28: =A28 -> Crédito Parcelado 19 | P28: =$O$5/19 -> 52.631579 | Q28: =$O$5*(1-D28) -> 811
A29: Crédito Parcelado 20x | B29: =$A$5/(1-D29) -> 1243.4718 | C29: =B29/20 -> 62.173589 | D29: 0.1958 | E29: =B29/$A$5 -> 1.2434718 | F29: =C29/$A$5 -> 0.062173589 | H29: =$A$5*J29 -> 1554.3397 | I29: =H29/20 -> 77.716986 | J29: =E29*(1+$K$7) -> 1.5543397 | K29: =I29/$A$5 -> 0.077716986 | O29: =A29 -> Crédito Parcelado 20x | P29: =$O$5/20 -> 50 | Q29: =$O$5*(1-D29) -> 804.2
A30: Crédito Parcelado 21x | B30: =$A$5/(1-D30) -> 1254.0757 | C30: =B30/21 -> 59.717893 | D30: 0.2026 | E30: =B30/$A$5 -> 1.2540757 | F30: =C30/$A$5 -> 0.059717893 | H30: =$A$5*J30 -> 1567.5947 | I30: =H30/21 -> 74.647366 | J30: =E30*(1+$K$7) -> 1.5675947 | K30: =I30/$A$5 -> 0.074647366 | O30: =A30 -> Crédito Parcelado 21x | P30: =$O$5/21 -> 47.619048 | Q30: =$O$5*(1-D30) -> 797.4
A32: Débito (Visa/Master) | B32: =$A$5/(1-D32) -> 1009.999 | C32: =B32 -> 1009.999 | D32: 0.0099 | E32: =C32/A5 -> 1.009999 | F32: =C32/A5 -> 1.009999 | H32: 111.56615 | I32: 111.56615 | J32: =E32*(1+$K$7) -> 1.2624987 | K32: 1.1156615 | O32: =A32 -> Débito (Visa/Master) | P32: =O5 -> 1000 | Q32: =$O$5*(1-D32) -> 990.1
A34: Débito (Elo, Hiper e Amex) | B34: =$A$5/(1-D34) -> 1009.999 | C34: =B34 -> 1009.999 | D34: 0.0099 | E34: =C34/A5 -> 1.009999 | F34: =C34/A5 -> 1.009999 | H34: 108.59543 | I34: 108.59543 | J34: =E34*(1+$K$7) -> 1.2624987 | K34: 1.0859543 | O34: =A34 -> Débito (Elo, Hiper e Amex) | P34: =O5 -> 1000 | Q34: =$O$5*(1-D34) -> 990.1

Sheet Planilha2
A2: 1
A3: 2
A4: 3
A5: 4
A6: 5
A7: 6
A8: 7
A9: 8
A10: 9
A11: 10
A12: 11
A13: 12
... A22: 21

Sheet Planilha1
A1: TABELA
A3: Parcelas | B3: 0.05 | C3: 0.07 | D3: 0.1 | E3: 0.12 | F3: 0.15 | G3: 0.17 | H3: 0.2 | I3: 0.25 | J3: 0.3
A4: 1 | B4: 1.0930668 | C4: 1.1138872 | D4: 1.1451176 | E4: 1.165938 | F4: 1.1971684 | G4: 1.2179888 | H4: 1.2492192 | I4: 1.30127 | J4: 1.3533208
A5: 2 | B5: 1.1050605 | C5: 1.1261093 | D5: 1.1576824 | E5: 1.1787312 | F5: 1.2103044 | G5: 1.2313531 | H5: 1.2629263 | I5: 1.3155482 | J5: 1.3681701
A6: 3 | B6: 1.1133115 | C6: 1.1345174 | D6: 1.1663263 | E6: 1.1875322 | F6: 1.2193411 | G6: 1.2405471 | H6: 1.272356 | I6: 1.3253708 | J6: 1.3783856
A7: 4 | B7: 1.1216866 | C7: 1.143052 | D7: 1.1751002 | E7: 1.1964657 | F7: 1.2285139 | G7: 1.2498793 | H7: 1.2819275 | I7: 1.3353412 | J7: 1.3887548
A8: 5 | B8: 1.1301886 | C8: 1.151716 | D8: 1.1840071 | E8: 1.2055345 | F8: 1.2378256 | G8: 1.2593531 | H8: 1.2916442 | I8: 1.3454627 | J8: 1.3992812
A9: 6 | B9: 1.1388206 | C9: 1.1605124 | D9: 1.1930501 | E9: 1.2147419 | F9: 1.2472797 | G9: 1.2689715 | H9: 1.3015092 | I9: 1.3557388 | J9: 1.4099683
A10: 7 | B10: 1.1524 | C10: 1.1743504 | D10: 1.2072761 | E10: 1.2292266 | F10: 1.2621523 | G10: 1.2841028 | H10: 1.3170285 | I10: 1.3719047 | J10: 1.4267809
A11: 8 | B11: 1.1616686 | C11: 1.1837956 | D11: 1.2169861 | E11: 1.2391132 | F11: 1.2723037 | G11: 1.2944307 | H11: 1.3276212 | I11: 1.3829388 | J11: 1.4382563
A12: 9 | B12: 1.1710875 | C12: 1.193394 | D12: 1.2268536 | E12: 1.24916 | F12: 1.2826197 | G12: 1.3049261 | H12: 1.3383857 | I12: 1.3941518 | J12: 1.4499179
A13: 10 | B13: 1.1806604 | C13: 1.2031492 | D13: 1.2368824 | E13: 1.2593711 | F13: 1.2931043 | G13: 1.3155931 | H13: 1.3493262 | I13: 1.4055481 | J13: 1.4617701
A14: 11 | B14: 1.1903912 | C14: 1.2130653 | D14: 1.2470765 | E14: 1.2697506 | F14: 1.3037617 | G14: 1.3264359 | H14: 1.360447 | I14: 1.4171323 | J14: 1.4738176
A15: 12 | B15: 1.2002836 | C15: 1.2231462 | D15: 1.25744 | E15: 1.2803025 | F15: 1.3145963 | G15: 1.3374589 | H15: 1.3717527 | I15: 1.4289091 | J15: 1.4860654
... A21: 18 | B21: 1.2632723 | C21: 1.2873346 | D21: 1.3234281 | E21: 1.3474904 | F21: 1.3835839 | G21: 1.4076462 | H21: 1.4437397 | I21: 1.5038955 | J21: 1.5640514
